{
	"lastBuildDate": "Tue, 18 Jun 2019 10:33:00 +0900",
	"display": 1,
	"start": 1,
	"items": [
		{
			"userRating": "0.00",
			"link": "https://movie.naver.com/movie/bi/mi/basic.nhn?code=172567",
			"director": "네지메 지로|",
			"image": "https://ssl.pstatic.net/imgmovie/mdi/mit110/1725/172567_P01_143134.jpg",
			"actor": "",
			"subtitle": "Heya ni kakusiteoita eroDVD wo gimusume ga katte ni miteirutokoro wo mokugekisitesimai",
			"pubDate": "2016",
			"title": "<b>근친</b>의 <b>사랑</b>3:<b>양아버지</b>"
		}
	],
	"total": 1
}