{
	"lastBuildDate": "Tue, 18 Jun 2019 10:03:23 +0900",
	"display": 1,
	"start": 1,
	"items": [
		{
			"userRating": "0.00",
			"link": "https://movie.naver.com/movie/bi/mi/basic.nhn?code=162562",
			"director": "에릭 부피스|마튜 체르니소브|",
			"image": "https://ssl.pstatic.net/imgmovie/mdi/mit110/1625/162562_P01_161713.jpg",
			"actor": "",
			"subtitle": "Solar Impulse, the Impossible Round the World Mission",
			"pubDate": "2017",
			"title": "솔라 임펄스, 디 <b>임파서블</b> 라운드 <b>더</b> 월드 미션"
		}
	],
	"total": 4
}