{
	"display": 1,
	"total": 1,
	"items": [
		{
			"pubDate": "2016",
			"link": "https://movie.naver.com/movie/bi/mi/basic.nhn?code=136835",
			"director": "안톤 후쿠아|",
			"actor": "크리스 프랫|에단 호크|덴젤 워싱턴|빈<b>센트</b> 도노프리오|맷 보머|피터 사스가드|캠 지갠뎃|헤일리 베넷|이병헌|비니 존스|마누엘 가르시아 룰포|마틴 센스마이어|",
			"image": "https://ssl.pstatic.net/imgmovie/mdi/mit110/1368/136835_P19_110642.jpg",
			"userRating": "7.92",
			"title": "<b>매그니피센트 7</b>",
			"subtitle": "The Magnificent Seven"
		}
	],
	"start": 1,
	"lastBuildDate": "Tue, 18 Jun 2019 09:59:54 +0900"
}