{
	"lastBuildDate": "Tue, 18 Jun 2019 10:10:34 +0900",
	"display": 1,
	"start": 1,
	"items": [
		{
			"userRating": "7.44",
			"link": "https://movie.naver.com/movie/bi/mi/basic.nhn?code=100635",
			"director": "다카하타 이사오|",
			"image": "https://ssl.pstatic.net/imgmovie/mdi/mit110/1006/100635_P11_121544.jpg",
			"actor": "",
			"subtitle": "赤毛のアン　グリ&amp;#12540;ンゲ&amp;#12540;ブルズへの道",
			"pubDate": "2010",
			"title": "<b>빨간</b><b>머리</b> <b>앤</b> : <b>그린</b><b>게이블</b>로 <b>가는</b> <b>길</b>"
		}
	],
	"total": 1
}