{
	"display": 1,
	"total": 2,
	"items": [
		{
			"pubDate": "2012",
			"link": "https://movie.naver.com/movie/bi/mi/basic.nhn?code=94506",
			"director": "벤 스타센|",
			"actor": "빌리 웅거|팻 캐럴|카를로스 맥쿨러스 2세|이사벨 퍼만|멜라니 그리피스|크리스 앤드류 시울라|신다 애덤스|테리 더글러스|카터 하스팅스|케이틀린 메이어|실리에 레이나모|더글러스 리안 로스|마이클 선 리|조 토마스|윌리 제임스 워렌 주니어|대런 카포지|",
			"image": "https://ssl.pstatic.net/imgmovie/mdi/mit110/0945/94506_P21_112038.jpg",
			"userRating": "8.63",
			"title": "<b>새미의 어드벤쳐</b> 2",
			"subtitle": "Sammy's avonturen 2"
		}
	],
	"start": 1,
	"lastBuildDate": "Tue, 18 Jun 2019 09:59:52 +0900"
}