{
	"display": 1,
	"total": 1,
	"lastBuildDate": "Mon, 17 Jun 2019 17:22:08 +0900",
	"start": 1,
	"items": [
		{
			"actor": "존 레귀자모|레이 로마노|데니스 리어리|퀸 라티파|제니퍼 로페즈|",
			"link": "https://movie.naver.com/movie/bi/mi/basic.nhn?code=82227",
			"subtitle": "Ice Age: Continental Drift",
			"userRating": "8.24",
			"director": "스티브 마티노|마이크 트메이어|",
			"title": "<b>아이스</b> <b>에이지</b> <b>4</b>: <b>대륙</b> <b>이동설</b>",
			"image": "https://ssl.pstatic.net/imgmovie/mdi/mit110/0822/82227_P38_135522.jpg",
			"pubDate": "2012"
		}
	]
}