{
	"lastBuildDate": "Tue, 18 Jun 2019 10:12:17 +0900",
	"display": 1,
	"start": 1,
	"items": [
		{
			"userRating": "8.10",
			"link": "https://movie.naver.com/movie/bi/mi/basic.nhn?code=178761",
			"director": "개리 앤드류스|",
			"image": "https://ssl.pstatic.net/imgmovie/mdi/mit110/1787/178761_P08_105024.jpg",
			"actor": "데이비드 테넌트|나이젤 휘트미|조연우|신정훈|박상우|방지원|송영인|오은수|",
			"subtitle": "Fireman Sam: Alien Alert! The Movie",
			"pubDate": "2016",
			"title": "<b>출동</b>! <b>소방관</b> <b>샘</b>: <b>외계인</b> <b>대소동</b>"
		}
	],
	"total": 1
}